littledarwin/JavaIO.py
littledarwin/JavaLexer.py
littledarwin/JavaMutate.py
littledarwin/JavaParse.py
littledarwin/JavaParser.py
littledarwin/License.py
littledarwin/LittleDarwin.py
littledarwin/ReportGenerator.py
littledarwin/__init__.py
littledarwin/__main__.py
littledarwin-0.11.0.dist-info/licenses/LICENSE.md
tests/__init__.py
tests/test_JavaMutate.py
tests/test_JavaParse.py
tests/test_LittleDarwin.py
littledarwin-0.11.0.dist-info/METADATA
littledarwin-0.11.0.dist-info/WHEEL
littledarwin-0.11.0.dist-info/entry_points.txt
littledarwin-0.11.0.dist-info/top_level.txt
littledarwin-0.11.0.dist-info/RECORD
