Metadata-Version: 2.4
Name: littledarwin
Version: 0.11.0
Summary: LittleDarwin Mutation Analysis Framework
Home-page: https://littledarwin.parsai.net/
Author: Ali Parsai
Author-email: ali.parsai@live.com
License: GNU GPLv3
Classifier: Programming Language :: Python :: 3
Classifier: License :: OSI Approved :: GNU General Public License v3 or later (GPLv3+)
Classifier: Operating System :: OS Independent
Requires-Python: >=3.5
License-File: LICENSE.md
Requires-Dist: antlr4-python3-runtime
Requires-Dist: graphviz
Dynamic: author
Dynamic: author-email
Dynamic: classifier
Dynamic: description
Dynamic: description-content-type
Dynamic: home-page
Dynamic: license
Dynamic: license-file
Dynamic: requires-dist
Dynamic: requires-python
Dynamic: summary
